{
  "multipart": [
    {
      "when": {
        "facing": "north"
      },
      "apply": { "model": "intercraftcore:block/treetap/treetap" }
    },
    {
      "when": {
        "facing": "south"
      },
      "apply": { "model": "intercraftcore:block/treetap/treetap", "uvlock": true, "y": 180 }
    },
    {
      "when": {
        "facing": "west"
      },
      "apply": { "model": "intercraftcore:block/treetap/treetap", "uvlock": true, "y": 270 }
    },
    {
      "when": {
        "facing": "east"
      },
      "apply": { "model": "intercraftcore:block/treetap/treetap", "uvlock": true, "y": 90 }
    },


    {
      "when": {
        "facing": "north", "bucket": "wood_oak"
      },
      "apply": { "model": "intercraftcore:block/treetap/wood_oak_bucket" }
    },
    {
      "when": {
        "facing": "south", "bucket": "wood_oak"
      },
      "apply": { "model": "intercraftcore:block/treetap/wood_oak_bucket", "uvlock": true, "y": 180 }
    },
    {
      "when": {
        "facing": "west", "bucket": "wood_oak"
      },
      "apply": { "model": "intercraftcore:block/treetap/wood_oak_bucket", "uvlock": true, "y": 270 }
    },
    {
      "when": {
        "facing": "east", "bucket": "wood_oak"
      },
      "apply": { "model": "intercraftcore:block/treetap/wood_oak_bucket", "uvlock": true, "y": 90 }
    },
    {
      "when": {
        "facing": "north", "bucket": "wood_spruce"
      },
      "apply": { "model": "intercraftcore:block/treetap/wood_spruce_bucket" }
    },
    {
      "when": {
        "facing": "south", "bucket": "wood_spruce"
      },
      "apply": { "model": "intercraftcore:block/treetap/wood_spruce_bucket", "uvlock": true, "y": 180 }
    },
    {
      "when": {
        "facing": "west", "bucket": "wood_spruce"
      },
      "apply": { "model": "intercraftcore:block/treetap/wood_spruce_bucket", "uvlock": true, "y": 270 }
    },
    {
      "when": {
        "facing": "east", "bucket": "wood_spruce"
      },
      "apply": { "model": "intercraftcore:block/treetap/wood_spruce_bucket", "uvlock": true, "y": 90 }
    },
    {
      "when": {
        "facing": "north", "bucket": "wood_birch"
      },
      "apply": { "model": "intercraftcore:block/treetap/wood_birch_bucket" }
    },
    {
      "when": {
        "facing": "south", "bucket": "wood_birch"
      },
      "apply": { "model": "intercraftcore:block/treetap/wood_birch_bucket", "uvlock": true, "y": 180 }
    },
    {
      "when": {
        "facing": "west", "bucket": "wood_birch"
      },
      "apply": { "model": "intercraftcore:block/treetap/wood_birch_bucket", "uvlock": true, "y": 270 }
    },
    {
      "when": {
        "facing": "east", "bucket": "wood_birch"
      },
      "apply": { "model": "intercraftcore:block/treetap/wood_birch_bucket", "uvlock": true, "y": 90 }
    },
    {
      "when": {
        "facing": "north", "bucket": "wood_jungle"
      },
      "apply": { "model": "intercraftcore:block/treetap/wood_jungle_bucket" }
    },
    {
      "when": {
        "facing": "south", "bucket": "wood_jungle"
      },
      "apply": { "model": "intercraftcore:block/treetap/wood_jungle_bucket", "uvlock": true, "y": 180 }
    },
    {
      "when": {
        "facing": "west", "bucket": "wood_jungle"
      },
      "apply": { "model": "intercraftcore:block/treetap/wood_jungle_bucket", "uvlock": true, "y": 270 }
    },
    {
      "when": {
        "facing": "east", "bucket": "wood_jungle"
      },
      "apply": { "model": "intercraftcore:block/treetap/wood_jungle_bucket", "uvlock": true, "y": 90 }
    },
    {
      "when": {
        "facing": "north", "bucket": "wood_acacia"
      },
      "apply": { "model": "intercraftcore:block/treetap/wood_acacia_bucket" }
    },
    {
      "when": {
        "facing": "south", "bucket": "wood_acacia"
      },
      "apply": { "model": "intercraftcore:block/treetap/wood_acacia_bucket", "uvlock": true, "y": 180 }
    },
    {
      "when": {
        "facing": "west", "bucket": "wood_acacia"
      },
      "apply": { "model": "intercraftcore:block/treetap/wood_acacia_bucket", "uvlock": true, "y": 270 }
    },
    {
      "when": {
        "facing": "east", "bucket": "wood_acacia"
      },
      "apply": { "model": "intercraftcore:block/treetap/wood_acacia_bucket", "uvlock": true, "y": 90 }
    },
    {
      "when": {
        "facing": "north", "bucket": "wood_dark_oak"
      },
      "apply": { "model": "intercraftcore:block/treetap/wood_dark_oak_bucket" }
    },
    {
      "when": {
        "facing": "south", "bucket": "wood_dark_oak"
      },
      "apply": { "model": "intercraftcore:block/treetap/wood_dark_oak_bucket", "uvlock": true, "y": 180 }
    },
    {
      "when": {
        "facing": "west", "bucket": "wood_dark_oak"
      },
      "apply": { "model": "intercraftcore:block/treetap/wood_dark_oak_bucket", "uvlock": true, "y": 270 }
    },
    {
      "when": {
        "facing": "east", "bucket": "wood_dark_oak"
      },
      "apply": { "model": "intercraftcore:block/treetap/wood_dark_oak_bucket", "uvlock": true, "y": 90 }
    },


    {
      "when": {
        "facing": "north", "bucket": "metal_iron"
      },
      "apply": { "model": "intercraftcore:block/treetap/metal_iron_bucket" }
    },
    {
      "when": {
        "facing": "south", "bucket": "metal_iron"
      },
      "apply": { "model": "intercraftcore:block/treetap/metal_iron_bucket", "uvlock": true, "y": 180 }
    },
    {
      "when": {
        "facing": "west", "bucket": "metal_iron"
      },
      "apply": { "model": "intercraftcore:block/treetap/metal_iron_bucket", "uvlock": true, "y": 270 }
    },
    {
      "when": {
        "facing": "east", "bucket": "metal_iron"
      },
      "apply": { "model": "intercraftcore:block/treetap/metal_iron_bucket", "uvlock": true, "y": 90 }
    }
  ]
}